{
    "output": {
        "bass_enhancer#0": {
            "amount": 3.0,
            "blend": 2.0,
            "bypass": false,
            "floor": 20.0,
            "floor-active": false,
            "harmonics": 8.0,
            "input-gain": -1.0,
            "output-gain": 0.3,
            "scope": 120.0
        },
        "blocklist": [],
        "crystalizer#0": {
            "band0": {
                "bypass": false,
                "intensity": 25.0,
                "mute": false
            },
            "band1": {
                "bypass": false,
                "intensity": 26.0,
                "mute": false
            },
            "band10": {
                "bypass": false,
                "intensity": -7.0,
                "mute": false
            },
            "band11": {
                "bypass": false,
                "intensity": -2.0,
                "mute": false
            },
            "band12": {
                "bypass": false,
                "intensity": -1.0,
                "mute": false
            },
            "band2": {
                "bypass": false,
                "intensity": 23.0,
                "mute": false
            },
            "band3": {
                "bypass": false,
                "intensity": 13.0,
                "mute": false
            },
            "band4": {
                "bypass": false,
                "intensity": 4.0,
                "mute": false
            },
            "band5": {
                "bypass": false,
                "intensity": -7.0,
                "mute": false
            },
            "band6": {
                "bypass": false,
                "intensity": -13.0,
                "mute": false
            },
            "band7": {
                "bypass": false,
                "intensity": -16.0,
                "mute": false
            },
            "band8": {
                "bypass": false,
                "intensity": -17.0,
                "mute": false
            },
            "band9": {
                "bypass": false,
                "intensity": -13.0,
                "mute": false
            },
            "bypass": false,
            "input-gain": -1.0,
            "output-gain": -0.5
        },
        "multiband_compressor#0": {
            "band0": {
                "attack-threshold": -12.0,
                "attack-time": 20.0,
                "boost-amount": 6.0,
                "boost-threshold": -72.0,
                "compression-mode": "Downward",
                "compressor-enable": true,
                "external-sidechain": false,
                "knee": -6.0,
                "makeup": 0.0,
                "mute": false,
                "ratio": 1.0,
                "release-threshold": -100.0,
                "release-time": 100.0,
                "sidechain-custom-highcut-filter": false,
                "sidechain-custom-lowcut-filter": false,
                "sidechain-highcut-frequency": 500.0,
                "sidechain-lookahead": 0.0,
                "sidechain-lowcut-frequency": 10.0,
                "sidechain-mode": "RMS",
                "sidechain-preamp": 0.0,
                "sidechain-reactivity": 10.0,
                "sidechain-source": "Middle",
                "solo": false,
                "stereo-split-source": "Left/Right"
            },
            "band1": {
                "attack-threshold": -12.0,
                "attack-time": 20.0,
                "boost-amount": 6.0,
                "boost-threshold": -72.0,
                "compression-mode": "Downward",
                "compressor-enable": true,
                "enable-band": true,
                "external-sidechain": false,
                "knee": -6.0,
                "makeup": 0.0,
                "mute": false,
                "ratio": 1.0,
                "release-threshold": -100.0,
                "release-time": 100.0,
                "sidechain-custom-highcut-filter": false,
                "sidechain-custom-lowcut-filter": false,
                "sidechain-highcut-frequency": 1000.0,
                "sidechain-lookahead": 0.0,
                "sidechain-lowcut-frequency": 500.0,
                "sidechain-mode": "RMS",
                "sidechain-preamp": 0.0,
                "sidechain-reactivity": 10.0,
                "sidechain-source": "Middle",
                "solo": false,
                "split-frequency": 500.0,
                "stereo-split-source": "Left/Right"
            },
            "band2": {
                "attack-threshold": -12.0,
                "attack-time": 20.0,
                "boost-amount": 6.0,
                "boost-threshold": -72.0,
                "compression-mode": "Downward",
                "compressor-enable": true,
                "enable-band": true,
                "external-sidechain": false,
                "knee": -6.0,
                "makeup": 0.0,
                "mute": false,
                "ratio": 1.0,
                "release-threshold": -100.0,
                "release-time": 100.0,
                "sidechain-custom-highcut-filter": false,
                "sidechain-custom-lowcut-filter": false,
                "sidechain-highcut-frequency": 2000.0,
                "sidechain-lookahead": 0.0,
                "sidechain-lowcut-frequency": 1000.0,
                "sidechain-mode": "RMS",
                "sidechain-preamp": 0.0,
                "sidechain-reactivity": 10.0,
                "sidechain-source": "Middle",
                "solo": false,
                "split-frequency": 1000.0,
                "stereo-split-source": "Left/Right"
            },
            "band3": {
                "attack-threshold": -12.0,
                "attack-time": 20.0,
                "boost-amount": 6.0,
                "boost-threshold": -72.0,
                "compression-mode": "Downward",
                "compressor-enable": true,
                "enable-band": true,
                "external-sidechain": false,
                "knee": -6.0,
                "makeup": 0.0,
                "mute": false,
                "ratio": 1.0,
                "release-threshold": -100.0,
                "release-time": 100.0,
                "sidechain-custom-highcut-filter": false,
                "sidechain-custom-lowcut-filter": false,
                "sidechain-highcut-frequency": 4000.0,
                "sidechain-lookahead": 0.0,
                "sidechain-lowcut-frequency": 2000.0,
                "sidechain-mode": "RMS",
                "sidechain-preamp": 0.0,
                "sidechain-reactivity": 10.0,
                "sidechain-source": "Middle",
                "solo": false,
                "split-frequency": 2000.0,
                "stereo-split-source": "Left/Right"
            },
            "band4": {
                "attack-threshold": -12.0,
                "attack-time": 20.0,
                "boost-amount": 6.0,
                "boost-threshold": -72.0,
                "compression-mode": "Downward",
                "compressor-enable": true,
                "enable-band": false,
                "external-sidechain": false,
                "knee": -6.0,
                "makeup": 0.0,
                "mute": false,
                "ratio": 1.0,
                "release-threshold": -100.0,
                "release-time": 100.0,
                "sidechain-custom-highcut-filter": false,
                "sidechain-custom-lowcut-filter": false,
                "sidechain-highcut-frequency": 8000.0,
                "sidechain-lookahead": 0.0,
                "sidechain-lowcut-frequency": 4000.0,
                "sidechain-mode": "RMS",
                "sidechain-preamp": 0.0,
                "sidechain-reactivity": 10.0,
                "sidechain-source": "Middle",
                "solo": false,
                "split-frequency": 4000.0,
                "stereo-split-source": "Left/Right"
            },
            "band5": {
                "attack-threshold": -12.0,
                "attack-time": 20.0,
                "boost-amount": 6.0,
                "boost-threshold": -72.0,
                "compression-mode": "Downward",
                "compressor-enable": true,
                "enable-band": false,
                "external-sidechain": false,
                "knee": -6.0,
                "makeup": 0.0,
                "mute": false,
                "ratio": 1.0,
                "release-threshold": -100.0,
                "release-time": 100.0,
                "sidechain-custom-highcut-filter": false,
                "sidechain-custom-lowcut-filter": false,
                "sidechain-highcut-frequency": 12000.0,
                "sidechain-lookahead": 0.0,
                "sidechain-lowcut-frequency": 8000.0,
                "sidechain-mode": "RMS",
                "sidechain-preamp": 0.0,
                "sidechain-reactivity": 10.0,
                "sidechain-source": "Middle",
                "solo": false,
                "split-frequency": 8000.0,
                "stereo-split-source": "Left/Right"
            },
            "band6": {
                "attack-threshold": -12.0,
                "attack-time": 20.0,
                "boost-amount": 6.0,
                "boost-threshold": -72.0,
                "compression-mode": "Downward",
                "compressor-enable": true,
                "enable-band": false,
                "external-sidechain": false,
                "knee": -6.0,
                "makeup": 0.0,
                "mute": false,
                "ratio": 1.0,
                "release-threshold": -100.0,
                "release-time": 100.0,
                "sidechain-custom-highcut-filter": false,
                "sidechain-custom-lowcut-filter": false,
                "sidechain-highcut-frequency": 16000.0,
                "sidechain-lookahead": 0.0,
                "sidechain-lowcut-frequency": 12000.0,
                "sidechain-mode": "RMS",
                "sidechain-preamp": 0.0,
                "sidechain-reactivity": 10.0,
                "sidechain-source": "Middle",
                "solo": false,
                "split-frequency": 12000.0,
                "stereo-split-source": "Left/Right"
            },
            "band7": {
                "attack-threshold": -12.0,
                "attack-time": 20.0,
                "boost-amount": 6.0,
                "boost-threshold": -72.0,
                "compression-mode": "Downward",
                "compressor-enable": true,
                "enable-band": false,
                "external-sidechain": false,
                "knee": -6.0,
                "makeup": 0.0,
                "mute": false,
                "ratio": 1.0,
                "release-threshold": -100.0,
                "release-time": 100.0,
                "sidechain-custom-highcut-filter": false,
                "sidechain-custom-lowcut-filter": false,
                "sidechain-highcut-frequency": 20000.0,
                "sidechain-lookahead": 0.0,
                "sidechain-lowcut-frequency": 16000.0,
                "sidechain-mode": "RMS",
                "sidechain-preamp": 0.0,
                "sidechain-reactivity": 10.0,
                "sidechain-source": "Middle",
                "solo": false,
                "split-frequency": 16000.0,
                "stereo-split-source": "Left/Right"
            },
            "bypass": false,
            "compressor-mode": "Modern",
            "dry": -100.0,
            "envelope-boost": "None",
            "input-gain": 0.0,
            "output-gain": 0.0,
            "stereo-split": false,
            "wet": 0.30000000000000004
        },
        "plugins_order": [
            "bass_enhancer#0",
            "crystalizer#0",
            "multiband_compressor#0"
        ]
    }
}
